PyDWI/__init__.py
PyDWI/_nbdev.py
PyDWI/core.py
PyDWI-0.0.1.dist-info/LICENSE
PyDWI-0.0.1.dist-info/METADATA
PyDWI-0.0.1.dist-info/WHEEL
PyDWI-0.0.1.dist-info/entry_points.txt
PyDWI-0.0.1.dist-info/top_level.txt
PyDWI-0.0.1.dist-info/RECORD
