Metadata-Version: 2.1
Name: PyDWI
Version: 0.0.1
Summary: Fast ADC and DKI maps
Home-page: https://github.com/gkaissis/PyDWI/tree/master/
Author: Georgios Kaissis
Author-email: gkaissis@users.noreply.github.com
License: Apache Software License 2.0
Keywords: Python,ADC,DWI,DKI,diffusion
Platform: UNKNOWN
Classifier: Development Status :: 4 - Beta
Classifier: Intended Audience :: Developers
Classifier: License :: OSI Approved :: Apache Software License
Classifier: Natural Language :: English
Classifier: Programming Language :: Python :: 3.7
Classifier: Programming Language :: Python :: 3.8
Requires-Python: >=3.7
Requires-Dist: numpy
Requires-Dist: nibabel
Requires-Dist: pydicom
Requires-Dist: scikit-learn
Requires-Dist: scipy
Requires-Dist: pandas
Requires-Dist: tqdm
Requires-Dist: matplotlib
